{"trial_id": "01debec2067bc305f98611e759a8fab7", "hyperparameters": {"space": [{"class_name": "Boolean", "config": {"name": "structured_data_block_1/normalize", "default": false, "conditions": []}}, {"class_name": "Boolean", "config": {"name": "structured_data_block_1/dense_block_1/use_batchnorm", "default": false, "conditions": []}}, {"class_name": "Choice", "config": {"name": "structured_data_block_1/dense_block_1/num_layers", "default": 2, "conditions": [], "values": [1, 2, 3], "ordered": true}}, {"class_name": "Choice", "config": {"name": "structured_data_block_1/dense_block_1/units_0", "default": 32, "conditions": [], "values": [16, 32, 64, 128, 256, 512, 1024], "ordered": true}}, {"class_name": "Choice", "config": {"name": "structured_data_block_1/dense_block_1/dropout", "default": 0.0, "conditions": [], "values": [0.0, 0.25, 0.5], "ordered": true}}, {"class_name": "Choice", "config": {"name": "structured_data_block_1/dense_block_1/units_1", "default": 32, "conditions": [], "values": [16, 32, 64, 128, 256, 512, 1024], "ordered": true}}, {"class_name": "Choice", "config": {"name": "regression_head_1/dropout", "default": 0, "conditions": [], "values": [0.0, 0.25, 0.5], "ordered": true}}, {"class_name": "Choice", "config": {"name": "optimizer", "default": "adam", "conditions": [], "values": ["adam", "sgd", "adam_weight_decay"], "ordered": false}}, {"class_name": "Choice", "config": {"name": "learning_rate", "default": 0.001, "conditions": [], "values": [0.1, 0.01, 0.001, 0.0001, 2e-05, 1e-05], "ordered": true}}], "values": {"structured_data_block_1/normalize": true, "structured_data_block_1/dense_block_1/use_batchnorm": true, "structured_data_block_1/dense_block_1/num_layers": 2, "structured_data_block_1/dense_block_1/units_0": 64, "structured_data_block_1/dense_block_1/dropout": 0.0, "structured_data_block_1/dense_block_1/units_1": 32, "regression_head_1/dropout": 0.0, "optimizer": "adam", "learning_rate": 0.001}}, "metrics": {"metrics": {"loss": {"direction": "min", "observations": [{"value": [557.1593627929688], "step": 0}, {"value": [13.808859825134277], "step": 1}, {"value": [13.446256637573242], "step": 2}, {"value": [13.295753479003906], "step": 3}, {"value": [13.193413734436035], "step": 4}, {"value": [13.123287200927734], "step": 5}, {"value": [13.071017265319824], "step": 6}, {"value": [13.026777267456055], "step": 7}, {"value": [12.9866943359375], "step": 8}, {"value": [12.951637268066406], "step": 9}, {"value": [12.922006607055664], "step": 10}, {"value": [12.894338607788086], "step": 11}, {"value": [12.868782043457031], "step": 12}, {"value": [12.846980094909668], "step": 13}]}, "mean_squared_error": {"direction": "min", "observations": [{"value": [557.1593627929688], "step": 0}, {"value": [13.808859825134277], "step": 1}, {"value": [13.446256637573242], "step": 2}, {"value": [13.295753479003906], "step": 3}, {"value": [13.193413734436035], "step": 4}, {"value": [13.123287200927734], "step": 5}, {"value": [13.071017265319824], "step": 6}, {"value": [13.026777267456055], "step": 7}, {"value": [12.9866943359375], "step": 8}, {"value": [12.951637268066406], "step": 9}, {"value": [12.922006607055664], "step": 10}, {"value": [12.894338607788086], "step": 11}, {"value": [12.868782043457031], "step": 12}, {"value": [12.846980094909668], "step": 13}]}, "val_loss": {"direction": "min", "observations": [{"value": [14.670226097106934], "step": 0}, {"value": [13.977947235107422], "step": 1}, {"value": [13.913064002990723], "step": 2}, {"value": [13.81502628326416], "step": 3}, {"value": [13.826851844787598], "step": 4}, {"value": [13.880463600158691], "step": 5}, {"value": [13.946499824523926], "step": 6}, {"value": [13.99960708618164], "step": 7}, {"value": [13.948151588439941], "step": 8}, {"value": [13.824371337890625], "step": 9}, {"value": [13.89576530456543], "step": 10}, {"value": [13.876547813415527], "step": 11}, {"value": [13.843194007873535], "step": 12}, {"value": [13.820819854736328], "step": 13}]}, "val_mean_squared_error": {"direction": "min", "observations": [{"value": [14.670226097106934], "step": 0}, {"value": [13.977947235107422], "step": 1}, {"value": [13.913064002990723], "step": 2}, {"value": [13.81502628326416], "step": 3}, {"value": [13.826851844787598], "step": 4}, {"value": [13.880463600158691], "step": 5}, {"value": [13.946499824523926], "step": 6}, {"value": [13.99960708618164], "step": 7}, {"value": [13.948151588439941], "step": 8}, {"value": [13.824371337890625], "step": 9}, {"value": [13.89576530456543], "step": 10}, {"value": [13.876547813415527], "step": 11}, {"value": [13.843194007873535], "step": 12}, {"value": [13.820819854736328], "step": 13}]}}}, "score": 13.81502628326416, "best_step": 3, "status": "COMPLETED"}